{
	"name": "Vimium C",
	"@time": "5/7/2025, 1:23:13 AM",
	"time": 1746555793293,
	"environment": {
		"extension": "2.12.2",
		"platform": "win",
		"chromium": 136
	},
	"allBrowserUrls": true,
	"exclusionListenHash": false,
	"exclusionRules": [
		{
			"passKeys": "",
			"pattern": ":https://mail.google.com/"
		},
		{
			"passKeys": "/ ",
			"pattern": ":https://github.com/"
		},
		{
			"passKeys": "",
			"pattern": ":file:///"
		}
	],
	"extAllowList": [
		"# modified versions of X New Tab and PDF Viewer,",
		"hdnehngglnbnehkfcidabjckinphnief",
		"nacjakoppgmdcpemlfnfegmlhipddanj",
		"onlpodkdakgonlmodbgapcbigpcimokd",
		"",
		"# EdgeTranslate",
		"bocbaocobfecmglnmeaeppambideimao",
		"bfdogplmndidlpjfhoijckpakkdjkkil",
		"",
		"# SalaDict",
		"cdonnmffkdaoajfknoeeecmchibpmkmg",
		"idghocbbahafpfhjnfhpbfbmpegphmmp",
		"chpcblajbmmlbhecpnnadmjmlbhkloji",
		"",
		"# yomitan",
		"likgccmbimhjbgkjambclfkhldnlhbnn",
		"iikmkjmpaadaobahmlepeloendndfphd",
		"",
		"#refined github",
		"hlepfoohegkhhmjieoechaddaejaokhf",
		"",
		"# NewTab Adapter",
		"cglpcedifkgalfdklahhcchnjepcckfn",
		"",
		"# Shortcuts Forwarding Tool",
		"clnalilglegcjmlgenoppklmfppddien",
		"",
		"# INFO: Multi Find",
		"dffaiikpbncahnghlfnkhagffaemhgfo",
		"# INFO: Mark My Search",
		"lijbnhoniejpjjgemoifpjklobhakinb",
		""
	],
	"filterLinkHints": true,
	"grabBackFocus": true,
	"keyLayout": 146,
	"keyMappings": [
		"#!no-check",
		"# unmapping overlay keybinding.",
		"unmap <c-e>",
		"unmap <c-y>",
		"unmap <a-c>",
		"unmap <a-s-c>",
		"# INFO: since ctrl-r is available now",
		"unmap B",
		"unmap r",
		"unmap R",
		"map R reloadTab",
		"# INFO: basic Tab navigation",
		"unmap <<",
		"unmap >>",
		"map < moveTabLeft",
		"map > moveTabRight",
		"unmap j",
		"unmap J",
		"unmap n",
		"unmap N",
		"unmap K",
		"unmap k",
		"map j nextTab",
		"map J previousTab",
		"map k previousTab",
		"map K nextTab",
		"",
		"unmap o",
		"unmap X",
		"unmap <f1>",
		"",
		"# INFO: Since too many pages use `/` for search, we have to unmap it.",
		"unmap ?",
		"unmap /",
		"# use ? instead. I use `ctrl f` `ctrl g` more anyway.",
		"",
		"unmap yy",
		"map Y copyCurrentUrl",
		"map yy copyWindowInfo type=\"tab\" format=\"[${title}](${url})\" ",
		"map <f7> copyWindowInfo format=\"[${title}](${url})\" join=\"\\n\"",
		" ",
		"unmap p",
		"map p openCopiedUrlInNewTab",
		"",
		"# same reason why <f1> is used for help.",
		"map <f1> showHelp",
		"",
		"",
		"unmap O",
		"map o Vomnibar.activateInNewTab",
		"map O Vomnibar.activate",
		"map D scrollPageUp",
		"",
		"# INFO: emacs-like movement",
		"mapkey <a-b> <f3edit>",
		"map <f3edit> editText run=\"move,backward,word,exec,move,\"",
		"",
		"mapkey <a-n> <f3go>",
		"map <f3go> editText run=\"move,forward,word,exec,move,\"",
		"",
		"# like `delete` key",
		"mapkey <c-d> <f3rmcf>",
		"map <f3rmcf> editText run=\"extend,forward,character,exec,delete,\"",
		"",
		"",
		"mapkey <c-x> <f3rmline>",
		"map <f3rmline> editText run=\"extend,forward,lineboundary,exec,delete,\"",
		"",
		"# INFO: FindMode",
		"map + LinkHints.activateCopyLinkUrl",
		"map = LinkHints.activateCopyLinkText",
		"",
		"unmap 0",
		"map 00 LinkHints.activateWithQueue",
		"map F LinkHints.activateSelect",
		"",
		"# INFO: some tab operations",
		"unmap t",
		"map tt restoreTab",
		"# map ;t reopenTab",
		"# map T restoreTab",
		"# map S Vomnibar.activateTabs",
		"map ;q removeTab goto=\"previous,near\" highlighted",
		"",
		"",
		"# unmap <a-u> ",
		"unmap L",
		"map <a-s-w> goToRoot",
		"map <a-s-up> goToRoot",
		"map <a-w> goUp",
		"map <a-up> goUp",
		"map <a-s> goBack",
		"map <a-s-s> goForward",
		"map <a-s-down> goForward",
		"map <a-down> goBack",
		"",
		"# mark ",
		"# map ' Marks.activate",
		"map \" Marks.activateCreate",
		"",
		"# others",
		"map ;s sortTabs",
		"map V LinkHints.activateSelect",
		"# map ' LinkHints.activateSelect",
		"",
		"# INFO: quick open tabs. This is for msEdge",
		"# HACK: very dirty those, this should be in browsers' settings",
		"map <c-h> createTab url=\"chrome://history/\"",
		"map <c-s-x> createTab url=\"chrome://extensions/\"",
		"",
		"# INFO: new tab",
		"map ;w moveTabToNewWindow",
		"",
		"# HACK: quick open this extension options",
		"map <c-s><c-s> createTab url=\"chrome-extension://hfjbmagddngcpeloejdejnfgbamkjaeg/pages/options.html\"",
		"map <c-s>s createTab url=\"chrome-extension://hfjbmagddngcpeloejdejnfgbamkjaeg/pages/options.html\"",
		"map ss createTab url=\"chrome-extension://hfjbmagddngcpeloejdejnfgbamkjaeg/pages/options.html\"",
		"",
		"# unmap most of `g` since it's important for some sites.",
		"unmap gs",
		"unmap gn",
		"unmap gf",
		"unmap gF",
		"unmap ge",
		"map e Vomnibar.activateEditUrlInNewTab",
		"",
		"# INFO: accessing insert mode in left hand",
		"map <s-enter> focusInput",
		"map aa focusInput",
		"map I LinkHints.activateCopyImage",
		"# enterInsertMode",
		"",
		"# INFO: ",
		"# unmap -",
		"# Follow the link labeled next or \">\" (use sed=true, patterns:string, rel:string, noRel, isNext)(goNext)",
		"",
		"map ]c goNext patterns=\"Close\"",
		"map [c goPrevious patterns=\"Close\"",
		"",
		"",
		"map ]s goNext patterns=\"search\"",
		"map [s goPrevious patterns=\"search\"",
		"",
		"# INFO: get link in HN/lobsters/other meta sites.",
		"map ghn createTab url=\"!hn\\u0020&\"",
		"",
		"# INFO: shortcut edit.",
		"map <c-s><c-k> createTab url=\"chrome://extensions/shortcuts\"",
		"map <c-s><c-b> createTab url=\"chrome://tracing\"",
		"",
		"map <c-,><c-,> createTab url=\"chrome://settings\"",
		"",
		"# HACK: testing Shortcut Forwarding Tools, as now it's only used within vimium",
		"# userCustomized1 = \"<c-s-w>\"",
		"# shortcut userCustomized1 command=\"Vomnibar.activateTabs\"",
		"shortcut userCustomized1 command=\"createTab\"",
		"",
		"map <c-[:i> reset",
		"",
		"# map . enterFindMode",
		"map / enterFindMode",
		"map n performFind",
		"map m performBackwardsFind",
		"map N performBackwardsFind",
		"map , findSelected",
		"map MM clearFindHistory",
		"",
		"unmap zH",
		"unmap zL",
		"map z passNextKey",
		"",
		"map :SS joinTabs",
		""
	],
	"keyupTime": 100,
	"linkHintCharacters": "1234qweas",
	"linkHintNumbers": "012345",
	"newTabUrl": "duckduckgo.com",
	"regexFindMode": true,
	"scrollStepSize": 120,
	"searchEngines": [
		"\\:i: vimium://sed/s/^//,lower\\ $S re= Lower case",
		"v.m|math: vimium://math\\ $S re= Calculate",
		"v.p: vimium://parse\\ $S re= Redo Search",
		"js\\:|Js: javascript:\\ $S; JavaScript",
		"",
		"# INFO: bml that I stole",
		"r: vimium://run/openBookmark#mask&title=bml_reddit_1&#value=$S Reddit",
		"",
		"# HACK: Search for bang syntax.",
		"dg|bang|!: https://duckduckgo.com/bangs?q=%s",
		"mg|mar: https://search.marginalia.nu/search?query=%s",
		"",
		"# INFO: not yet available in bang syntax. May never be as well.",
		"kg|kagi: https://kagi.com/search?q=%s",
		""
	],
	"searchUrl": "https://duckduckgo.com/?q=$s DuckDuckGo",
	"vimSync": true,
	"vomnibarOptions": {
		"actions": "opener",
		"maxMatches": 10,
		"queryInterval": 100,
		"sizes": "77,3,44,0.8,1944",
		"styles": "mono-url"
	},
	"waitForEnter": false,
	"ignoreCapsLock": 2,
	"mapModifier": 2
}
